{"prematchData":{"teams":{"radiant":{"team_tag":"IP","has_logo":false,"team_id":6185655,"country":"cn","team_name":"IamPoint Club"},"dire":{"team_tag":"MAX","has_logo":true,"team_id":3325252,"country":"cn","team_name":"TEAM MAX"}},"bans":{"radiant":[{"is_pick":false,"hero_id":62,"team":0,"order":1},{"is_pick":false,"hero_id":52,"team":0,"order":3},{"is_pick":false,"hero_id":88,"team":0,"order":5},{"is_pick":false,"hero_id":10,"team":0,"order":11},{"is_pick":false,"hero_id":65,"team":0,"order":13},{"is_pick":false,"hero_id":63,"team":0,"order":18}],"dire":[{"is_pick":false,"hero_id":53,"team":1,"order":0},{"is_pick":false,"hero_id":18,"team":1,"order":2},{"is_pick":false,"hero_id":66,"team":1,"order":4},{"is_pick":false,"hero_id":85,"team":1,"order":10},{"is_pick":false,"hero_id":76,"team":1,"order":12},{"is_pick":false,"hero_id":28,"team":1,"order":19}]},"picks":{"radiant":[{"is_pick":true,"hero_id":109,"team":0,"order":7},{"is_pick":true,"hero_id":20,"team":0,"order":8},{"is_pick":true,"hero_id":15,"team":0,"order":14},{"is_pick":true,"hero_id":110,"team":0,"order":16},{"is_pick":true,"hero_id":120,"team":0,"order":21}],"dire":[{"is_pick":true,"hero_id":111,"team":1,"order":6},{"is_pick":true,"hero_id":23,"team":1,"order":9},{"is_pick":true,"hero_id":119,"team":1,"order":15},{"is_pick":true,"hero_id":39,"team":1,"order":17},{"is_pick":true,"hero_id":54,"team":1,"order":20}]},"league":{"id":10806,"url":"www.futurecup.net","tier":2,"name":"CHINA FUTURE  CUP","image":true},"rosters":{"radiant":[{"team":0,"name":"frost","hero_id":120,"account_id":237578577},{"team":0,"name":"HW","hero_id":110,"account_id":240727522},{"team":0,"name":"\u2606pinksoda\u2605","hero_id":20,"account_id":101663906},{"team":0,"name":"juju^ \u9972\u517b\u5458\u4e2b","hero_id":15,"account_id":104611628},{"team":0,"name":"No Role Modelz","hero_id":109,"account_id":171211166}],"dire":[{"team":1,"name":"SOS","hero_id":23,"account_id":179603165},{"team":1,"name":"\u559d\u5976","hero_id":111,"account_id":293529846},{"team":1,"name":"\u6d41\u661f\u6cea","hero_id":119,"account_id":150961567},{"team":1,"name":"Xhd","hero_id":39,"account_id":138522697},{"team":1,"name":"ANI","hero_id":54,"account_id":129852226}]}},"aftermatchData":{"score":{"radiant":22,"dire":16},"duration":1885,"winner":"radiant"}}