{"prematchData":{"teams":{"radiant":{"country":"ph","team_name":"TaskUs TITANS","team_tag":"TITANS","team_id":5063845,"has_logo":true},"dire":{"country":"cn","team_name":"Photon Gaming","team_tag":"PG","team_id":7034601,"has_logo":true}},"bans":{"radiant":[{"is_pick":false,"hero_id":76,"team":0,"order":1},{"is_pick":false,"hero_id":33,"team":0,"order":3},{"is_pick":false,"hero_id":111,"team":0,"order":5},{"is_pick":false,"hero_id":121,"team":0,"order":11},{"is_pick":false,"hero_id":63,"team":0,"order":13},{"is_pick":false,"hero_id":39,"team":0,"order":18}],"dire":[{"is_pick":false,"hero_id":88,"team":1,"order":0},{"is_pick":false,"hero_id":10,"team":1,"order":2},{"is_pick":false,"hero_id":52,"team":1,"order":4},{"is_pick":false,"hero_id":95,"team":1,"order":10},{"is_pick":false,"hero_id":102,"team":1,"order":12},{"is_pick":false,"hero_id":70,"team":1,"order":19}]},"picks":{"radiant":[{"is_pick":true,"hero_id":107,"team":0,"order":7},{"is_pick":true,"hero_id":55,"team":0,"order":8},{"is_pick":true,"hero_id":15,"team":0,"order":14},{"is_pick":true,"hero_id":65,"team":0,"order":16},{"is_pick":true,"hero_id":94,"team":0,"order":21}],"dire":[{"is_pick":true,"hero_id":20,"team":1,"order":6},{"is_pick":true,"hero_id":69,"team":1,"order":9},{"is_pick":true,"hero_id":66,"team":1,"order":15},{"is_pick":true,"hero_id":8,"team":1,"order":17},{"is_pick":true,"hero_id":120,"team":1,"order":20}]},"league":{"id":10741,"tier":2,"image":true,"name":"rainbow cup","url":"dotamax.com"},"rosters":{"radiant":[{"hero_id":65,"team":0,"account_id":126941616,"name":"Frenkie"},{"hero_id":55,"team":0,"account_id":308570784,"name":"H.God"},{"hero_id":15,"team":0,"account_id":362653751,"name":"iu-god"},{"hero_id":94,"team":0,"account_id":101897410,"name":"miggeL.z"},{"hero_id":107,"team":0,"account_id":156029808,"name":"mode: TI9 PLAYER"}],"dire":[{"hero_id":8,"team":1,"account_id":256238640,"name":"\u547c\u5438"},{"hero_id":66,"team":1,"account_id":193790070,"name":"sfffff"},{"hero_id":120,"team":1,"account_id":407235798,"name":"W T F"},{"hero_id":20,"team":1,"account_id":929988762,"name":"cefzon"},{"hero_id":69,"team":1,"account_id":399861473,"name":"\u51b2\u51fb\u5149\u62f3"}]}},"aftermatchData":{"score":{"radiant":7,"dire":23},"duration":1190,"winner":"dire"}}