{"prematchData":{"teams":{"radiant":{"country":"my","team_tag":"WG","team_id":7118594,"has_logo":true,"team_name":"Warriors Gaming"},"dire":{"country":"my","team_tag":"MYSGAU","team_id":7119284,"has_logo":false,"team_name":"Power of MYSG+AU"}},"bans":{"radiant":[{"is_pick":false,"hero_id":6,"team":0,"order":1},{"is_pick":false,"hero_id":69,"team":0,"order":3},{"is_pick":false,"hero_id":55,"team":0,"order":5},{"is_pick":false,"hero_id":52,"team":0,"order":11},{"is_pick":false,"hero_id":96,"team":0,"order":13},{"is_pick":false,"hero_id":29,"team":0,"order":18}],"dire":[{"is_pick":false,"hero_id":102,"team":1,"order":0},{"is_pick":false,"hero_id":65,"team":1,"order":2},{"is_pick":false,"hero_id":88,"team":1,"order":4},{"is_pick":false,"hero_id":10,"team":1,"order":10},{"is_pick":false,"hero_id":18,"team":1,"order":12},{"is_pick":false,"hero_id":23,"team":1,"order":19}]},"picks":{"radiant":[{"is_pick":true,"hero_id":121,"team":0,"order":7},{"is_pick":true,"hero_id":16,"team":0,"order":8},{"is_pick":true,"hero_id":97,"team":0,"order":14},{"is_pick":true,"hero_id":44,"team":0,"order":16},{"is_pick":true,"hero_id":25,"team":0,"order":21}],"dire":[{"is_pick":true,"hero_id":33,"team":1,"order":6},{"is_pick":true,"hero_id":8,"team":1,"order":9},{"is_pick":true,"hero_id":31,"team":1,"order":15},{"is_pick":true,"hero_id":45,"team":1,"order":17},{"is_pick":true,"hero_id":104,"team":1,"order":20}]},"league":{"name":"EPICENTER Major 2019","image":true,"url":"http:\/\/epicenter.gg\/","id":10826,"tier":3},"rosters":{"radiant":[{"name":"TNC.Sam H","account_id":187619311,"hero_id":16,"team":0},{"name":"IU-day","account_id":177085220,"hero_id":25,"team":0},{"name":"\u0412\u043f\u0443\u0441\u0442\u0443\u044e","account_id":412753955,"hero_id":44,"team":0},{"name":"wdnmd","account_id":119535307,"hero_id":97,"team":0},{"name":"MoonS","account_id":38628747,"hero_id":121,"team":0}],"dire":[{"name":"poloson","account_id":76904792,"hero_id":33,"team":1},{"name":"vtF\u03b1ded","account_id":142139318,"hero_id":8,"team":1},{"name":"Mski-X.WinteR","account_id":86762037,"hero_id":31,"team":1},{"name":"NothingToSay","account_id":173978074,"hero_id":45,"team":1},{"name":"Saitama","account_id":110539311,"hero_id":104,"team":1}]}},"aftermatchData":{"score":{"radiant":7,"dire":19},"duration":1987,"winner":"dire"}}