{"prematchData":{"teams":{"radiant":{"team_id":2634810,"team_name":"KEENGAMING.LUMINOUS","has_logo":true,"team_tag":"KGL","country":"cn"},"dire":{"team_id":1089226,"team_name":"Beyond Alliance","has_logo":false,"team_tag":"BA","country":""}},"bans":{"radiant":[{"is_pick":false,"hero_id":6,"team":0,"order":1},{"is_pick":false,"hero_id":102,"team":0,"order":3},{"is_pick":false,"hero_id":69,"team":0,"order":5},{"is_pick":false,"hero_id":10,"team":0,"order":11},{"is_pick":false,"hero_id":100,"team":0,"order":13},{"is_pick":false,"hero_id":39,"team":0,"order":18}],"dire":[{"is_pick":false,"hero_id":88,"team":1,"order":0},{"is_pick":false,"hero_id":33,"team":1,"order":2},{"is_pick":false,"hero_id":53,"team":1,"order":4},{"is_pick":false,"hero_id":27,"team":1,"order":10},{"is_pick":false,"hero_id":52,"team":1,"order":12},{"is_pick":false,"hero_id":45,"team":1,"order":19}]},"picks":{"radiant":[{"is_pick":true,"hero_id":15,"team":0,"order":7},{"is_pick":true,"hero_id":87,"team":0,"order":8},{"is_pick":true,"hero_id":86,"team":0,"order":14},{"is_pick":true,"hero_id":42,"team":0,"order":16},{"is_pick":true,"hero_id":61,"team":0,"order":21}],"dire":[{"is_pick":true,"hero_id":111,"team":1,"order":6},{"is_pick":true,"hero_id":16,"team":1,"order":9},{"is_pick":true,"hero_id":55,"team":1,"order":15},{"is_pick":true,"hero_id":109,"team":1,"order":17},{"is_pick":true,"hero_id":76,"team":1,"order":20}]},"league":{"tier":2,"url":"https:\/\/www.varena.com\/","name":"VARENA\u8d5b\u4e8b","image":true,"id":10365},"rosters":{"radiant":[{"team":0,"hero_id":86,"name":"\u7ec4\u88c5\u73bb\u7483\u7247(\u0e51\u2022\u0300\u3142\u2022\u0301)\u0648","account_id":411596849},{"team":0,"hero_id":42,"name":"Yo","account_id":185646215},{"team":0,"hero_id":61,"name":"\u9cb8\u843d","account_id":315272623},{"team":0,"hero_id":15,"name":"\u4e70\u53f7\u4f53\u9a8c\u9ad8\u5206\u5c40","account_id":313744564},{"team":0,"hero_id":87,"name":"\u6700\u540e\u7684\u9a91\u58eb","account_id":136980762}],"dire":[{"team":1,"hero_id":76,"name":"\u5148\u5d29","account_id":136891448},{"team":1,"hero_id":111,"name":"\u4e7e\u5764\u6717\u6717","account_id":102158434},{"team":1,"hero_id":16,"name":"\u4e09\u623f\u59e8\u592a\u592a","account_id":44282162},{"team":1,"hero_id":55,"name":"Andre","account_id":147480469},{"team":1,"hero_id":109,"name":"tokyo","account_id":218497450}]}},"aftermatchData":{"score":{"radiant":15,"dire":5},"duration":1614,"winner":"radiant"}}