{"prematchData":{"teams":{"radiant":{"team_id":6797380,"team_name":"AMPLFY","team_tag":"AMPLFY","country":"ph","has_logo":true},"dire":{"team_id":7098928,"team_name":"Adroit","team_tag":"Adroit","country":"ph","has_logo":true}},"bans":{"radiant":[{"is_pick":false,"hero_id":66,"team":0,"order":0},{"is_pick":false,"hero_id":16,"team":0,"order":2},{"is_pick":false,"hero_id":89,"team":0,"order":4},{"is_pick":false,"hero_id":44,"team":0,"order":10},{"is_pick":false,"hero_id":43,"team":0,"order":12},{"is_pick":false,"hero_id":8,"team":0,"order":19}],"dire":[{"is_pick":false,"hero_id":33,"team":1,"order":1},{"is_pick":false,"hero_id":106,"team":1,"order":3},{"is_pick":false,"hero_id":42,"team":1,"order":5},{"is_pick":false,"hero_id":129,"team":1,"order":11},{"is_pick":false,"hero_id":13,"team":1,"order":13},{"is_pick":false,"hero_id":3,"team":1,"order":18}]},"picks":{"radiant":[{"is_pick":true,"hero_id":91,"team":0,"order":6},{"is_pick":true,"hero_id":72,"team":0,"order":9},{"is_pick":true,"hero_id":38,"team":0,"order":15},{"is_pick":true,"hero_id":49,"team":0,"order":17},{"is_pick":true,"hero_id":83,"team":0,"order":20}],"dire":[{"is_pick":true,"hero_id":97,"team":1,"order":7},{"is_pick":true,"hero_id":79,"team":1,"order":8},{"is_pick":true,"hero_id":96,"team":1,"order":14},{"is_pick":true,"hero_id":45,"team":1,"order":16},{"is_pick":true,"hero_id":18,"team":1,"order":21}]},"league":{"tier":3,"id":10749,"image":true,"name":"The International 2019","url":"https:\/\/www.dota2.com\/international"},"rosters":{"radiant":[{"hero_id":91,"team":0,"account_id":156029808,"name":"mode: TI9 player"},{"hero_id":83,"team":0,"account_id":87360406,"name":"Jeyo"},{"hero_id":38,"team":0,"account_id":115102590,"name":"ryOyr"},{"hero_id":49,"team":0,"account_id":94281932,"name":"K"},{"hero_id":72,"team":0,"account_id":119898344,"name":"ABAT"}],"dire":[{"hero_id":97,"team":1,"account_id":127077041,"name":"CG.Boombacs"},{"hero_id":18,"team":1,"account_id":355168766,"name":"close to you"},{"hero_id":45,"team":1,"account_id":104512126,"name":"FUCK DOTAAAAAAAAAA!!!!"},{"hero_id":96,"team":1,"account_id":113874152,"name":"WE HAWT! Bok!"},{"hero_id":79,"team":1,"account_id":100616105,"name":"cml"}]}},"aftermatchData":{"score":{"radiant":5,"dire":11},"duration":1941,"winner":"dire"}}