{"prematchData":{"teams":{"radiant":{"team_name":"Team Elephant","team_tag":null,"has_logo":true,"country":"","team_id":7268813},"dire":{"team_name":"GUYS","team_tag":null,"has_logo":false,"country":"","team_id":7056890}},"bans":{"radiant":[{"is_pick":false,"hero_id":33,"team":0,"order":0},{"is_pick":false,"hero_id":52,"team":0,"order":2},{"is_pick":false,"hero_id":85,"team":0,"order":4},{"is_pick":false,"hero_id":95,"team":0,"order":10},{"is_pick":false,"hero_id":96,"team":0,"order":12},{"is_pick":false,"hero_id":76,"team":0,"order":19}],"dire":[{"is_pick":false,"hero_id":91,"team":1,"order":1},{"is_pick":false,"hero_id":129,"team":1,"order":3},{"is_pick":false,"hero_id":25,"team":1,"order":5},{"is_pick":false,"hero_id":65,"team":1,"order":11},{"is_pick":false,"hero_id":16,"team":1,"order":13},{"is_pick":false,"hero_id":23,"team":1,"order":18}]},"picks":{"radiant":[{"is_pick":true,"hero_id":68,"team":0,"order":6},{"is_pick":true,"hero_id":42,"team":0,"order":9},{"is_pick":true,"hero_id":79,"team":0,"order":15},{"is_pick":true,"hero_id":40,"team":0,"order":17},{"is_pick":true,"hero_id":106,"team":0,"order":20}],"dire":[{"is_pick":true,"hero_id":111,"team":1,"order":7},{"is_pick":true,"hero_id":27,"team":1,"order":8},{"is_pick":true,"hero_id":57,"team":1,"order":14},{"is_pick":true,"hero_id":18,"team":1,"order":16},{"is_pick":true,"hero_id":17,"team":1,"order":21}]},"league":{"tier":2,"image":true,"name":"redrain cup","url":"dotamax.com","id":10944},"rosters":{"radiant":[{"team":0,"hero_id":106,"name":"\u4e8c\u5e08\u5f1f\u4e36","account_id":161137480},{"team":0,"hero_id":68,"name":"\u53e4\u5929\u4e50","account_id":361452834},{"team":0,"hero_id":42,"name":"Malin","account_id":436237192},{"team":0,"hero_id":79,"name":"Forest.","account_id":376845967},{"team":0,"hero_id":40,"name":"Kix","account_id":889401261}],"dire":[{"team":1,"hero_id":111,"name":"Zerotwo","account_id":136421659},{"team":1,"hero_id":17,"name":"\u5f88\u9177\u4e0d\u8bf4\u8bdd\u5c0f\u864e","account_id":175538337},{"team":1,"hero_id":57,"name":"h","account_id":994051399},{"team":1,"hero_id":18,"name":"awuwu","account_id":334050219},{"team":1,"hero_id":27,"name":"Docres","account_id":130503714}]}},"aftermatchData":{"score":{"radiant":15,"dire":14},"duration":1775,"winner":"radiant"}}