{"prematchData":{"teams":{"radiant":{"country":"cn","team_name":"Royal","team_tag":"Royal","has_logo":true,"team_id":6382740},"dire":{"country":"cn","team_name":"iG.Vitality","team_tag":"iG.V","has_logo":true,"team_id":2640025}},"bans":{"radiant":[{"is_pick":false,"hero_id":91,"team":0,"order":1},{"is_pick":false,"hero_id":79,"team":0,"order":3},{"is_pick":false,"hero_id":25,"team":0,"order":5},{"is_pick":false,"hero_id":121,"team":0,"order":11},{"is_pick":false,"hero_id":47,"team":0,"order":13},{"is_pick":false,"hero_id":21,"team":0,"order":18}],"dire":[{"is_pick":false,"hero_id":33,"team":1,"order":0},{"is_pick":false,"hero_id":73,"team":1,"order":2},{"is_pick":false,"hero_id":84,"team":1,"order":4},{"is_pick":false,"hero_id":50,"team":1,"order":10},{"is_pick":false,"hero_id":90,"team":1,"order":12},{"is_pick":false,"hero_id":76,"team":1,"order":19}]},"picks":{"radiant":[{"is_pick":true,"hero_id":111,"team":0,"order":7},{"is_pick":true,"hero_id":99,"team":0,"order":8},{"is_pick":true,"hero_id":27,"team":0,"order":14},{"is_pick":true,"hero_id":43,"team":0,"order":16},{"is_pick":true,"hero_id":14,"team":0,"order":21}],"dire":[{"is_pick":true,"hero_id":106,"team":1,"order":6},{"is_pick":true,"hero_id":107,"team":1,"order":9},{"is_pick":true,"hero_id":31,"team":1,"order":15},{"is_pick":true,"hero_id":58,"team":1,"order":17},{"is_pick":true,"hero_id":41,"team":1,"order":20}]},"league":{"url":"http:\/\/www.imbatv.cn\/","name":"\u4e2d\u56fdDOTA2\u53d1\u5c55\u8054\u8d5b","image":true,"tier":2,"id":11099},"rosters":{"radiant":[{"name":"\u6fd1\u7531\u8863","account_id":89598554,"hero_id":27,"team":0},{"name":"\u4fee   \u884c","account_id":108221389,"hero_id":111,"team":0},{"name":"G \u00ec \u00d6 R \u00d1 \u00f3 G \u00ec \u00d2 \u03bd \u00c2 \u00f1 \u00f1 \u00c0 -","account_id":136177710,"hero_id":14,"team":0},{"name":"hh","account_id":373520478,"hero_id":43,"team":0},{"name":"\u65e0\u8138\u7537","account_id":156662698,"hero_id":99,"team":0}],"dire":[{"name":"\u5fc3\u6709\u6797\u5915","account_id":199222238,"hero_id":41,"team":1},{"name":"ButterflyEffect","account_id":137895298,"hero_id":106,"team":1},{"name":"Myth","account_id":139031324,"hero_id":58,"team":1},{"name":"Post Malone","account_id":197849259,"hero_id":107,"team":1},{"name":"< blank >","account_id":162077924,"hero_id":31,"team":1}]}},"aftermatchData":{"score":{"radiant":8,"dire":20},"duration":1691,"winner":"dire"}}