{"prematchData":{"teams":{"radiant":{"team_id":6187657,"country":"ph","has_logo":true,"team_name":"Neon Esports","team_tag":"neon"},"dire":{"team_id":7300685,"country":"cn","has_logo":true,"team_name":"Team Drinking","team_tag":"TD"}},"bans":{"radiant":[{"is_pick":false,"hero_id":71,"team":0,"order":0},{"is_pick":false,"hero_id":50,"team":0,"order":2},{"is_pick":false,"hero_id":83,"team":0,"order":4},{"is_pick":false,"hero_id":43,"team":0,"order":10},{"is_pick":false,"hero_id":65,"team":0,"order":12},{"is_pick":false,"hero_id":93,"team":0,"order":19}],"dire":[{"is_pick":false,"hero_id":66,"team":1,"order":1},{"is_pick":false,"hero_id":97,"team":1,"order":3},{"is_pick":false,"hero_id":99,"team":1,"order":5},{"is_pick":false,"hero_id":54,"team":1,"order":11},{"is_pick":false,"hero_id":18,"team":1,"order":13},{"is_pick":false,"hero_id":10,"team":1,"order":18}]},"picks":{"radiant":[{"is_pick":true,"hero_id":25,"team":0,"order":6},{"is_pick":true,"hero_id":84,"team":0,"order":9},{"is_pick":true,"hero_id":16,"team":0,"order":15},{"is_pick":true,"hero_id":98,"team":0,"order":17},{"is_pick":true,"hero_id":95,"team":0,"order":20}],"dire":[{"is_pick":true,"hero_id":79,"team":1,"order":7},{"is_pick":true,"hero_id":19,"team":1,"order":8},{"is_pick":true,"hero_id":52,"team":1,"order":14},{"is_pick":true,"hero_id":23,"team":1,"order":16},{"is_pick":true,"hero_id":76,"team":1,"order":21}]},"league":{"id":11140,"tier":2,"image":true,"name":"Destiny Cup","url":"www.dotamax.com"},"rosters":{"radiant":[{"team":0,"hero_id":84,"account_id":94733211,"name":"hhh"},{"team":0,"hero_id":98,"account_id":422952818,"name":"N"},{"team":0,"hero_id":95,"account_id":177061558,"name":"Young God"},{"team":0,"hero_id":25,"account_id":324277900,"name":"yopaj"},{"team":0,"hero_id":16,"account_id":345803031,"name":"KikonG*"}],"dire":[{"team":1,"hero_id":52,"account_id":404529913,"name":"Kusunoki 1999"},{"team":1,"hero_id":79,"account_id":996294961,"name":"\u029a\u5976\u7cd6\u025e"},{"team":1,"hero_id":23,"account_id":888539956,"name":"\u4f60\u4eec\u7684\u5669\u68a6"},{"team":1,"hero_id":76,"account_id":106265700,"name":"biu."},{"team":1,"hero_id":19,"account_id":896458274,"name":"321"}]}},"aftermatchData":{"score":{"radiant":21,"dire":29},"duration":2023,"winner":"dire"}}