{"prematchData":{"teams":{"radiant":{"has_logo":true,"team_name":"Reality Rift","team_tag":"RR ","country":"sg","team_id":7404529},"dire":{"has_logo":true,"team_name":"WOLF","team_tag":null,"country":"ph","team_id":7217630}},"bans":{"radiant":[{"is_pick":false,"hero_id":52,"team":0,"order":1},{"is_pick":false,"hero_id":60,"team":0,"order":3},{"is_pick":false,"hero_id":103,"team":0,"order":5},{"is_pick":false,"hero_id":93,"team":0,"order":11},{"is_pick":false,"hero_id":41,"team":0,"order":13},{"is_pick":false,"hero_id":9,"team":0,"order":18}],"dire":[{"is_pick":false,"hero_id":79,"team":1,"order":0},{"is_pick":false,"hero_id":58,"team":1,"order":2},{"is_pick":false,"hero_id":19,"team":1,"order":4},{"is_pick":false,"hero_id":45,"team":1,"order":10},{"is_pick":false,"hero_id":25,"team":1,"order":12},{"is_pick":false,"hero_id":61,"team":1,"order":19}]},"picks":{"radiant":[{"is_pick":true,"hero_id":10,"team":0,"order":7},{"is_pick":true,"hero_id":7,"team":0,"order":8},{"is_pick":true,"hero_id":3,"team":0,"order":14},{"is_pick":true,"hero_id":88,"team":0,"order":16},{"is_pick":true,"hero_id":44,"team":0,"order":21}],"dire":[{"is_pick":true,"hero_id":90,"team":1,"order":6},{"is_pick":true,"hero_id":76,"team":1,"order":9},{"is_pick":true,"hero_id":84,"team":1,"order":15},{"is_pick":true,"hero_id":6,"team":1,"order":17},{"is_pick":true,"hero_id":53,"team":1,"order":20}]},"league":{"id":11160,"tier":2,"name":"Asian DOTA2 Gold Occupation Invitational Competition S3","image":true,"url":"www.vpgame.com"},"rosters":{"radiant":[{"hero_id":7,"name":"DGS01","team":0,"account_id":91644707},{"hero_id":10,"name":"` AlaCrity -","team":0,"account_id":118233883},{"hero_id":88,"name":"RR.Hustla","team":0,"account_id":343084576},{"hero_id":3,"name":"\u90b1\u5fb7\u52c7","team":0,"account_id":89603649},{"hero_id":44,"name":"RR.Luk","team":0,"account_id":163392533}],"dire":[{"hero_id":76,"name":"sHow es","team":1,"account_id":880093059},{"hero_id":53,"name":"InsidiousC","team":1,"account_id":377420354},{"hero_id":6,"name":"Azur4","team":1,"account_id":244058707},{"hero_id":90,"name":"snei0-sn","team":1,"account_id":117106216},{"hero_id":84,"name":"Asuna","team":1,"account_id":908221052}]}},"aftermatchData":{"score":{"radiant":14,"dire":18},"duration":1887,"winner":"dire"}}