{"prematchData":{"teams":{"radiant":{"team_id":7441091,"team_tag":"MyM","team_name":"My Mytanty","has_logo":false,"country":"ru"},"dire":{"team_id":6711721,"team_tag":"gOLD","team_name":"Old but Gold","has_logo":true,"country":"ru"}},"bans":{"radiant":[{"is_pick":false,"hero_id":79,"team":0,"order":1},{"is_pick":false,"hero_id":52,"team":0,"order":3},{"is_pick":false,"hero_id":19,"team":0,"order":5},{"is_pick":false,"hero_id":9,"team":0,"order":11},{"is_pick":false,"hero_id":41,"team":0,"order":13},{"is_pick":false,"hero_id":54,"team":0,"order":18}],"dire":[{"is_pick":false,"hero_id":38,"team":1,"order":0},{"is_pick":false,"hero_id":72,"team":1,"order":2},{"is_pick":false,"hero_id":83,"team":1,"order":4},{"is_pick":false,"hero_id":76,"team":1,"order":10},{"is_pick":false,"hero_id":106,"team":1,"order":12},{"is_pick":false,"hero_id":36,"team":1,"order":19}]},"picks":{"radiant":[{"is_pick":true,"hero_id":86,"team":0,"order":7},{"is_pick":true,"hero_id":96,"team":0,"order":8},{"is_pick":true,"hero_id":37,"team":0,"order":14},{"is_pick":true,"hero_id":8,"team":0,"order":16},{"is_pick":true,"hero_id":17,"team":0,"order":21}],"dire":[{"is_pick":true,"hero_id":23,"team":1,"order":6},{"is_pick":true,"hero_id":85,"team":1,"order":9},{"is_pick":true,"hero_id":119,"team":1,"order":15},{"is_pick":true,"hero_id":2,"team":1,"order":17},{"is_pick":true,"hero_id":15,"team":1,"order":20}]},"league":{"url":"http:\/\/www.marslive.cn\/","id":11280,"name":"MDL Chengdu Major","tier":3,"image":true},"rosters":{"radiant":[{"account_id":103850210,"team":0,"name":"\u0412\u0440\u0435\u043c\u044f \u0432 \u043d\u0438\u043a\u0443\u0434\u0430","hero_id":96},{"account_id":106278629,"team":0,"name":"Mufasa (fan)","hero_id":17},{"account_id":122644914,"team":0,"name":"neks","hero_id":86},{"account_id":401024207,"team":0,"name":"get things done or die","hero_id":37},{"account_id":150748346,"team":0,"name":"\u043c\u0443\u0442\u0430hT","hero_id":8}],"dire":[{"account_id":82305765,"team":1,"name":"\u041d\u0435\u0443\u043d\u044b\u0432\u0430\u044e\u0438\u0449\u0439 \u041a\u043e\u043c\u0430\u043d\u0434\u043e\u0440","hero_id":119},{"account_id":26316691,"team":1,"name":"Illidan Stormrage","hero_id":15},{"account_id":11550182,"team":1,"name":"VANSKOR","hero_id":85},{"account_id":87586992,"team":1,"name":"Positiffcheg","hero_id":23},{"account_id":96196828,"team":1,"name":"633","hero_id":2}]}},"aftermatchData":{"score":{"radiant":23,"dire":34},"duration":2010,"winner":"dire"}}