{"prematchData":{"teams":{"radiant":{"team_id":7121518,"has_logo":true,"team_tag":"UNK","country":"pe","team_name":"Unknown Team"},"dire":{"team_id":67,"has_logo":true,"team_tag":"paiN","country":"br","team_name":"paiN Gaming"}},"bans":{"radiant":[{"is_pick":false,"hero_id":105,"team":0,"order":0},{"is_pick":false,"hero_id":23,"team":0,"order":2},{"is_pick":false,"hero_id":66,"team":0,"order":4},{"is_pick":false,"hero_id":84,"team":0,"order":10},{"is_pick":false,"hero_id":85,"team":0,"order":12},{"is_pick":false,"hero_id":106,"team":0,"order":19}],"dire":[{"is_pick":false,"hero_id":59,"team":1,"order":1},{"is_pick":false,"hero_id":102,"team":1,"order":3},{"is_pick":false,"hero_id":90,"team":1,"order":5},{"is_pick":false,"hero_id":57,"team":1,"order":11},{"is_pick":false,"hero_id":104,"team":1,"order":13},{"is_pick":false,"hero_id":2,"team":1,"order":18}]},"picks":{"radiant":[{"is_pick":true,"hero_id":25,"team":0,"order":6},{"is_pick":true,"hero_id":112,"team":0,"order":9},{"is_pick":true,"hero_id":42,"team":0,"order":15},{"is_pick":true,"hero_id":45,"team":0,"order":17},{"is_pick":true,"hero_id":69,"team":0,"order":20}],"dire":[{"is_pick":true,"hero_id":97,"team":1,"order":7},{"is_pick":true,"hero_id":41,"team":1,"order":8},{"is_pick":true,"hero_id":101,"team":1,"order":14},{"is_pick":true,"hero_id":121,"team":1,"order":16},{"is_pick":true,"hero_id":74,"team":1,"order":21}]},"league":{"url":"http:\/\/www.marslive.cn\/","image":true,"name":"MDL Chengdu Major","id":11280,"tier":3},"rosters":{"radiant":[{"hero_id":25,"name":"nico","team":0,"account_id":86850560},{"hero_id":112,"name":"AD","team":0,"account_id":100758751},{"hero_id":42,"name":"Berna| coram Deo","team":0,"account_id":173971950},{"hero_id":69,"name":"changes","team":0,"account_id":109455705},{"hero_id":45,"name":"rapea con flow hpta","team":0,"account_id":91364275}],"dire":[{"hero_id":97,"name":"lelis","team":1,"account_id":87063175},{"hero_id":121,"name":"somewhere","team":1,"account_id":234237646},{"hero_id":101,"name":"galatasaray","team":1,"account_id":105045291},{"hero_id":74,"name":"Worthless","team":1,"account_id":85937380},{"hero_id":41,"name":"ssssssssssssssssssssssssssssssss","team":1,"account_id":94004717}]}},"aftermatchData":{"score":{"radiant":16,"dire":23},"duration":2248,"winner":"dire"}}