{"prematchData":{"teams":{"radiant":{"team_tag":"FTM","country":"ru","has_logo":true,"team_name":"FlyToMoon","team_id":6953913},"dire":{"team_tag":"Liquid","country":"","has_logo":true,"team_name":"Team Liquid","team_id":2163}},"bans":{"radiant":[{"is_pick":false,"hero_id":23,"team":0,"order":1},{"is_pick":false,"hero_id":72,"team":0,"order":3},{"is_pick":false,"hero_id":90,"team":0,"order":5},{"is_pick":false,"hero_id":112,"team":0,"order":11},{"is_pick":false,"hero_id":89,"team":0,"order":13},{"is_pick":false,"hero_id":42,"team":0,"order":18}],"dire":[{"is_pick":false,"hero_id":84,"team":1,"order":0},{"is_pick":false,"hero_id":38,"team":1,"order":2},{"is_pick":false,"hero_id":79,"team":1,"order":4},{"is_pick":false,"hero_id":96,"team":1,"order":10},{"is_pick":false,"hero_id":2,"team":1,"order":12},{"is_pick":false,"hero_id":19,"team":1,"order":19}]},"picks":{"radiant":[{"is_pick":true,"hero_id":86,"team":0,"order":7},{"is_pick":true,"hero_id":41,"team":0,"order":8},{"is_pick":true,"hero_id":85,"team":0,"order":14},{"is_pick":true,"hero_id":104,"team":0,"order":16},{"is_pick":true,"hero_id":29,"team":0,"order":21}],"dire":[{"is_pick":true,"hero_id":102,"team":1,"order":6},{"is_pick":true,"hero_id":52,"team":1,"order":9},{"is_pick":true,"hero_id":30,"team":1,"order":15},{"is_pick":true,"hero_id":61,"team":1,"order":17},{"is_pick":true,"hero_id":106,"team":1,"order":20}]},"league":{"image":true,"id":11349,"url":"https:\/\/dreamhack.com\/dreamleague","name":"Corsair DreamLeague Season 12","tier":2},"rosters":{"radiant":[{"hero_id":86,"name":"Slayer","account_id":91460772,"team":0},{"hero_id":41,"name":".kelen'","account_id":96189126,"team":0},{"hero_id":104,"name":"Flow","account_id":91932652,"team":0},{"hero_id":29,"name":"Iceberg","account_id":250114507,"team":0},{"hero_id":85,"name":"ALWAYSWANNAFLY","account_id":91064780,"team":0}],"dire":[{"hero_id":52,"name":"Liquid.Taiga\u2764","account_id":401792574,"team":1},{"hero_id":30,"name":"Liquid.iNSaNiA","account_id":54580962,"team":1},{"hero_id":106,"name":"Liquid.miCKe","account_id":152962063,"team":1},{"hero_id":61,"name":"Liquid.qojqva","account_id":86738694,"team":1},{"hero_id":102,"name":"Liquid.boxi","account_id":77490514,"team":1}]}},"aftermatchData":{"score":{"radiant":20,"dire":25},"duration":2553,"winner":"radiant"}}