{"prematchData":{"teams":{"radiant":{"country":null,"has_logo":false,"team_tag":"","team_name":"","team_id":-1},"dire":{"country":"cn","has_logo":true,"team_tag":"TP","team_name":"Team Patience","team_id":7356557}},"bans":{"radiant":[{"is_pick":false,"hero_id":60,"team":0,"order":1},{"is_pick":false,"hero_id":90,"team":0,"order":3},{"is_pick":false,"hero_id":23,"team":0,"order":5},{"is_pick":false,"hero_id":29,"team":0,"order":11},{"is_pick":false,"hero_id":76,"team":0,"order":13},{"is_pick":false,"hero_id":74,"team":0,"order":18}],"dire":[{"is_pick":false,"hero_id":7,"team":1,"order":0},{"is_pick":false,"hero_id":52,"team":1,"order":2},{"is_pick":false,"hero_id":41,"team":1,"order":4},{"is_pick":false,"hero_id":72,"team":1,"order":10},{"is_pick":false,"hero_id":106,"team":1,"order":12},{"is_pick":false,"hero_id":43,"team":1,"order":19}]},"picks":{"radiant":[{"is_pick":true,"hero_id":102,"team":0,"order":7},{"is_pick":true,"hero_id":96,"team":0,"order":8},{"is_pick":true,"hero_id":25,"team":0,"order":14},{"is_pick":true,"hero_id":4,"team":0,"order":16},{"is_pick":true,"hero_id":92,"team":0,"order":21}],"dire":[{"is_pick":true,"hero_id":9,"team":1,"order":6},{"is_pick":true,"hero_id":84,"team":1,"order":9},{"is_pick":true,"hero_id":93,"team":1,"order":15},{"is_pick":true,"hero_id":19,"team":1,"order":17},{"is_pick":true,"hero_id":47,"team":1,"order":20}]},"league":{"name":"Asia Dota2 Master League S2","url":"https:\/\/www.varena.com\/","image":true,"tier":1,"id":11320},"rosters":{"radiant":[{"account_id":103296177,"name":"\u6211\u5c31\u662f\u6ca1\u8111\u5b50\u5566","team":0,"hero_id":102},{"account_id":145957968,"name":"\u7ec3","team":0,"hero_id":96},{"account_id":138522697,"name":"Xhd\u2661Cy","team":0,"hero_id":4},{"account_id":227657377,"name":"Ahm'sol miskath Ozh.","team":0,"hero_id":92},{"account_id":136700299,"name":"xixi","team":0,"hero_id":25}],"dire":[{"account_id":996294961,"name":"ju","team":1,"hero_id":84},{"account_id":199534585,"name":"MF.1983","team":1,"hero_id":47},{"account_id":365351539,"name":"Topson","team":1,"hero_id":19},{"account_id":308143458,"name":"ffffffffff","team":1,"hero_id":9},{"account_id":406618249,"name":"CLA1250","team":1,"hero_id":93}]}},"aftermatchData":{"score":{"radiant":14,"dire":11},"duration":2089,"winner":"radiant"}}