{"prematchData":{"teams":{"radiant":{"team_name":"Blaze","team_id":7470549,"country":"","team_tag":null,"has_logo":true},"dire":{"team_name":"","team_id":-1,"country":null,"team_tag":"","has_logo":false}},"bans":{"radiant":[{"is_pick":false,"hero_id":60,"team":0,"order":1},{"is_pick":false,"hero_id":90,"team":0,"order":3},{"is_pick":false,"hero_id":38,"team":0,"order":5},{"is_pick":false,"hero_id":101,"team":0,"order":11},{"is_pick":false,"hero_id":9,"team":0,"order":13},{"is_pick":false,"hero_id":29,"team":0,"order":18}],"dire":[{"is_pick":false,"hero_id":92,"team":1,"order":0},{"is_pick":false,"hero_id":23,"team":1,"order":2},{"is_pick":false,"hero_id":79,"team":1,"order":4},{"is_pick":false,"hero_id":77,"team":1,"order":10},{"is_pick":false,"hero_id":72,"team":1,"order":12},{"is_pick":false,"hero_id":89,"team":1,"order":19}]},"picks":{"radiant":[{"is_pick":true,"hero_id":96,"team":0,"order":7},{"is_pick":true,"hero_id":25,"team":0,"order":8},{"is_pick":true,"hero_id":102,"team":0,"order":14},{"is_pick":true,"hero_id":19,"team":0,"order":16},{"is_pick":true,"hero_id":11,"team":0,"order":21}],"dire":[{"is_pick":true,"hero_id":41,"team":1,"order":6},{"is_pick":true,"hero_id":84,"team":1,"order":9},{"is_pick":true,"hero_id":86,"team":1,"order":15},{"is_pick":true,"hero_id":46,"team":1,"order":17},{"is_pick":true,"hero_id":52,"team":1,"order":20}]},"league":{"name":"Asia Dota2 Master League S2","image":true,"tier":1,"url":"https:\/\/www.varena.com\/","id":11320},"rosters":{"radiant":[{"name":"\u6211\u5c31\u662f\u6ca1\u8111\u5b50\u5566","account_id":103296177,"team":0,"hero_id":102},{"name":"e ,","account_id":227657377,"team":0,"hero_id":11},{"name":"Xhd\u2661Cy","account_id":138522697,"team":0,"hero_id":19},{"name":"\u7ec3","account_id":145957968,"team":0,"hero_id":96},{"name":"xixi","account_id":136700299,"team":0,"hero_id":25}],"dire":[{"name":"\u60dc\u7f18","account_id":186080700,"team":1,"hero_id":84},{"name":"ty","account_id":86874930,"team":1,"hero_id":46},{"name":"\u6d41\u5149\u8bb0","account_id":140680642,"team":1,"hero_id":86},{"name":"\u4f60\u5f00\u5fc3\u5c31\u597d","account_id":96928450,"team":1,"hero_id":41},{"name":"......","account_id":111291593,"team":1,"hero_id":52}]}},"aftermatchData":{"score":{"radiant":15,"dire":6},"duration":1310,"winner":"radiant"}}