{"prematchData":{"teams":{"radiant":{"team_name":"Eclipse","has_logo":true,"country":"cn","team_tag":null,"team_id":5970391},"dire":{"team_name":"Neon Esports","has_logo":true,"country":"ph","team_tag":"neon","team_id":6187657}},"bans":{"radiant":[{"is_pick":false,"hero_id":60,"team":0,"order":0},{"is_pick":false,"hero_id":84,"team":0,"order":2},{"is_pick":false,"hero_id":72,"team":0,"order":4},{"is_pick":false,"hero_id":85,"team":0,"order":10},{"is_pick":false,"hero_id":37,"team":0,"order":12},{"is_pick":false,"hero_id":29,"team":0,"order":19}],"dire":[{"is_pick":false,"hero_id":90,"team":1,"order":1},{"is_pick":false,"hero_id":23,"team":1,"order":3},{"is_pick":false,"hero_id":7,"team":1,"order":5},{"is_pick":false,"hero_id":12,"team":1,"order":11},{"is_pick":false,"hero_id":93,"team":1,"order":13},{"is_pick":false,"hero_id":89,"team":1,"order":18}]},"picks":{"radiant":[{"is_pick":true,"hero_id":25,"team":0,"order":6},{"is_pick":true,"hero_id":16,"team":0,"order":9},{"is_pick":true,"hero_id":31,"team":0,"order":15},{"is_pick":true,"hero_id":104,"team":0,"order":17},{"is_pick":true,"hero_id":35,"team":0,"order":20}],"dire":[{"is_pick":true,"hero_id":46,"team":1,"order":7},{"is_pick":true,"hero_id":40,"team":1,"order":8},{"is_pick":true,"hero_id":86,"team":1,"order":14},{"is_pick":true,"hero_id":66,"team":1,"order":16},{"is_pick":true,"hero_id":6,"team":1,"order":21}]},"league":{"url":"dotamax.com","id":11326,"tier":2,"image":true,"name":"God\u8054\u8d5b"},"rosters":{"radiant":[{"hero_id":35,"account_id":396221331,"team":0,"name":"\u897f\u74dc\u4fdd\u719f\u561b\uff1f"},{"hero_id":16,"account_id":1023965968,"team":0,"name":"\u4e4c\u9e26"},{"hero_id":25,"account_id":970029279,"team":0,"name":"K\u6b4c\u4e4b\u738b"},{"hero_id":31,"account_id":317849786,"team":0,"name":"\u54c6\u5566\u7f8e"},{"hero_id":104,"account_id":262367336,"team":0,"name":"Chariot"}],"dire":[{"hero_id":46,"account_id":324277900,"team":1,"name":"Yopajqt"},{"hero_id":6,"account_id":100594231,"team":1,"name":">"},{"hero_id":66,"account_id":323792491,"team":1,"name":"its my lucky day"},{"hero_id":40,"account_id":121833213,"team":1,"name":"Captain Price"},{"hero_id":86,"account_id":345803031,"team":1,"name":"PlayHard-"}]}},"aftermatchData":{"score":{"radiant":5,"dire":15},"duration":1284,"winner":"dire"}}